{"block": [{"text": "30", "paragraph": [{"text": "30", "word": ["30"], "bounding_poly": [[[35, 7], [45, 7], [45, 16], [35, 16]]]}], "bounding_poly": [[[35, 7], [45, 7], [45, 16], [35, 16]]]}, {"text": "70", "paragraph": [{"text": "70", "word": ["70"], "bounding_poly": [[[504, 8], [512, 8], [512, 16], [504, 16]]]}], "bounding_poly": [[[504, 8], [512, 8], [512, 16], [504, 16]]]}, {"text": "60", "paragraph": [{"text": "60", "word": ["60"], "bounding_poly": [[[504, 39], [512, 39], [512, 46], [504, 46]]]}], "bounding_poly": [[[504, 39], [512, 39], [512, 46], [504, 46]]]}, {"text": "25", "paragraph": [{"text": "25", "word": ["25"], "bounding_poly": [[[35, 43], [45, 43], [45, 52], [35, 52]]]}], "bounding_poly": [[[35, 43], [45, 43], [45, 52], [35, 52]]]}, {"text": "50", "paragraph": [{"text": "50", "word": ["50"], "bounding_poly": [[[505, 70], [513, 70], [513, 78], [505, 78]]]}], "bounding_poly": [[[505, 70], [513, 70], [513, 78], [505, 78]]]}, {"text": "20", "paragraph": [{"text": "20", "word": ["20"], "bounding_poly": [[[35, 79], [45, 79], [45, 87], [35, 87]]]}], "bounding_poly": [[[35, 79], [45, 79], [45, 87], [35, 87]]]}, {"text": ".", "paragraph": [{"text": ".", "word": ["."], "bounding_poly": [[[502, 96], [502, 94], [513, 94], [513, 96]]]}], "bounding_poly": [[[502, 96], [502, 94], [513, 94], [513, 96]]]}, {"text": "40", "paragraph": [{"text": "40", "word": ["40"], "bounding_poly": [[[504, 100], [513, 100], [513, 108], [504, 108]]]}], "bounding_poly": [[[504, 100], [513, 100], [513, 108], [504, 108]]]}, {"text": "Number of Occurrences", "paragraph": [{"text": "Number of Occurrences", "word": ["Number", "of", "Occurrences"], "bounding_poly": [[[11, 192], [11, 143], [25, 143], [25, 192]], [[11, 137], [11, 126], [25, 126], [25, 137]], [[11, 121], [11, 46], [25, 46], [25, 121]]]}], "bounding_poly": [[[11, 192], [12, 46], [26, 46], [25, 192]]]}, {"text": "15", "paragraph": [{"text": "15", "word": ["15"], "bounding_poly": [[[36, 115], [45, 115], [45, 124], [36, 124]]]}], "bounding_poly": [[[36, 115], [45, 115], [45, 124], [36, 124]]]}, {"text": "30", "paragraph": [{"text": "30", "word": ["30"], "bounding_poly": [[[504, 130], [512, 130], [512, 139], [504, 139]]]}], "bounding_poly": [[[504, 130], [512, 130], [512, 139], [504, 139]]]}, {"text": "10", "paragraph": [{"text": "10", "word": ["10"], "bounding_poly": [[[36, 152], [46, 152], [46, 160], [36, 160]]]}], "bounding_poly": [[[36, 152], [46, 152], [46, 160], [36, 160]]]}, {"text": "20", "paragraph": [{"text": "20", "word": ["20"], "bounding_poly": [[[504, 161], [512, 161], [512, 169], [504, 169]]]}], "bounding_poly": [[[504, 161], [512, 161], [512, 169], [504, 169]]]}, {"text": "5", "paragraph": [{"text": "5", "word": ["5"], "bounding_poly": [[[41, 186], [45, 186], [45, 196], [41, 196]]]}], "bounding_poly": [[[41, 186], [45, 186], [45, 196], [41, 196]]]}, {"text": "10", "paragraph": [{"text": "10", "word": ["10"], "bounding_poly": [[[504, 192], [512, 192], [512, 199], [504, 199]]]}], "bounding_poly": [[[504, 192], [512, 192], [512, 199], [504, 199]]]}, {"text": "0", "paragraph": [{"text": "0", "word": ["0"], "bounding_poly": [[[41, 222], [45, 222], [45, 230], [41, 230]]]}], "bounding_poly": [[[41, 222], [45, 222], [45, 230], [41, 230]]]}, {"text": "0", "paragraph": [{"text": "0", "word": ["0"], "bounding_poly": [[[503, 223], [507, 223], [507, 229], [503, 229]]]}], "bounding_poly": [[[503, 223], [507, 223], [507, 229], [503, 229]]]}, {"text": "Winter 2013", "paragraph": [{"text": "Winter 2013", "word": ["Winter", "2013"], "bounding_poly": [[[70, 234], [98, 235], [98, 245], [70, 244]], [[73, 247], [92, 247], [92, 257], [73, 257]]]}], "bounding_poly": [[[70, 234], [98, 234], [98, 257], [70, 257]]]}, {"text": "Fall 2014", "paragraph": [{"text": "Fall 2014", "word": ["Fall", "2014"], "bounding_poly": [[[457, 235], [472, 235], [472, 244], [457, 244]], [[456, 247], [475, 247], [475, 258], [456, 258]]]}], "bounding_poly": [[[456, 235], [475, 235], [475, 258], [456, 258]]]}, {"text": "2014", "paragraph": [{"text": "2014", "word": ["2014"], "bounding_poly": [[[291, 248], [311, 246], [312, 256], [292, 258]]]}], "bounding_poly": [[[291, 248], [311, 246], [312, 256], [292, 258]]]}, {"text": "Spring Summer Fall Winter Spring Summer 2013 2013 2013 2014 2014 ( pm25_stayhigh ; w [ 0-1 ] wind_stayhigh ) ; asthma_outbreak -pm25_stayhigh ; w [ 0-1 ] wind_stayhigh - * - pm25_stayhigh --wind_stay High", "paragraph": [{"text": "Spring Summer Fall Winter Spring Summer 2013 2013 2013", "word": ["Spring", "Summer", "Fall", "Winter", "Spring", "Summer", "2013", "2013", "2013"], "bounding_poly": [[[125, 234], [152, 234], [152, 248], [125, 248]], [[176, 235], [211, 235], [211, 244], [176, 244]], [[240, 235], [255, 235], [255, 244], [240, 244]], [[288, 235], [317, 235], [317, 245], [288, 245]], [[343, 233], [370, 234], [370, 248], [343, 247]], [[394, 235], [429, 235], [429, 245], [394, 245]], [[130, 247], [149, 247], [149, 259], [130, 259]], [[184, 248], [204, 248], [204, 260], [184, 260]], [[238, 248], [258, 248], [258, 258], [238, 258]]]}, {"text": "2014 2014 ( pm25_stayhigh ; w [ 0-1 ] wind_stayhigh ) ; asthma_outbreak", "word": ["2014", "2014", "(", "pm25_stayhigh", ";", "w", "[", "0-1", "]", "wind_stayhigh", ")", ";", "asthma_outbreak"], "bounding_poly": [[[347, 248], [367, 248], [367, 258], [347, 258]], [[400, 247], [420, 246], [420, 256], [400, 257]], [[132, 272], [142, 272], [142, 290], [132, 290]], [[143, 272], [212, 272], [212, 290], [143, 290]], [[217, 272], [218, 272], [218, 290], [217, 290]], [[223, 272], [226, 272], [226, 290], [223, 290]], [[234, 272], [236, 272], [236, 290], [234, 290]], [[237, 272], [250, 272], [250, 290], [237, 290]], [[251, 272], [253, 272], [253, 290], [251, 290]], [[255, 272], [320, 272], [320, 290], [255, 290]], [[323, 272], [325, 272], [325, 290], [323, 290]], [[328, 272], [330, 272], [330, 290], [328, 290]], [[333, 272], [415, 272], [415, 290], [333, 290]]]}, {"text": "-pm25_stayhigh ; w [ 0-1 ] wind_stayhigh - * - pm25_stayhigh --wind_stay High", "word": ["-pm25_stayhigh", ";", "w", "[", "0-1", "]", "wind_stayhigh", "-", "*", "-", "pm25_stayhigh", "--wind_stay", "High"], "bounding_poly": [[[132, 293], [209, 293], [209, 310], [132, 310]], [[213, 293], [215, 293], [215, 310], [213, 310]], [[219, 293], [223, 293], [223, 310], [219, 310]], [[230, 293], [232, 293], [232, 310], [230, 310]], [[233, 293], [244, 293], [244, 310], [233, 310]], [[248, 293], [250, 293], [250, 310], [248, 310]], [[250, 293], [317, 293], [317, 310], [250, 310]], [[112, 315], [117, 315], [117, 329], [112, 329]], [[120, 315], [126, 315], [126, 329], [120, 329]], [[129, 315], [134, 315], [134, 329], [129, 329]], [[142, 315], [212, 316], [212, 331], [142, 330]], [[111, 334], [184, 335], [184, 351], [111, 350]], [[185, 336], [207, 336], [207, 351], [185, 351]]]}], "bounding_poly": [[[125, 232], [429, 233], [429, 261], [125, 260]], [[132, 246], [420, 246], [420, 290], [132, 290]], [[111, 293], [317, 293], [317, 351], [111, 351]]]}], "bounding_poly": [[[35, 7], [45, 7], [45, 16], [35, 16]], [[504, 8], [512, 8], [512, 16], [504, 16]], [[504, 39], [512, 39], [512, 46], [504, 46]], [[35, 43], [45, 43], [45, 52], [35, 52]], [[505, 70], [513, 70], [513, 78], [505, 78]], [[35, 79], [45, 79], [45, 87], [35, 87]], [[502, 96], [502, 94], [513, 94], [513, 96]], [[504, 100], [513, 100], [513, 108], [504, 108]], [[11, 192], [12, 46], [26, 46], [25, 192]], [[36, 115], [45, 115], [45, 124], [36, 124]], [[504, 130], [512, 130], [512, 139], [504, 139]], [[36, 152], [46, 152], [46, 160], [36, 160]], [[504, 161], [512, 161], [512, 169], [504, 169]], [[41, 186], [45, 186], [45, 196], [41, 196]], [[504, 192], [512, 192], [512, 199], [504, 199]], [[41, 222], [45, 222], [45, 230], [41, 230]], [[503, 223], [507, 223], [507, 229], [503, 229]], [[70, 234], [98, 234], [98, 257], [70, 257]], [[456, 235], [475, 235], [475, 258], [456, 258]], [[291, 248], [311, 246], [312, 256], [292, 258]], [[111, 232], [429, 233], [429, 352], [111, 351]]]}