{"block": [{"text": "180,000", "paragraph": [{"text": "180,000", "word": ["180,000"], "bounding_poly": [[[41, 24], [84, 24], [84, 38], [41, 38]]]}], "bounding_poly": [[[41, 24], [84, 24], [84, 38], [41, 38]]]}, {"text": "-Blind spot", "paragraph": [{"text": "-Blind spot", "word": ["-Blind", "spot"], "bounding_poly": [[[325, 35], [367, 37], [366, 54], [324, 52]], [[372, 37], [400, 38], [399, 55], [371, 54]]]}], "bounding_poly": [[[325, 35], [400, 38], [399, 55], [324, 52]]]}, {"text": "160,000", "paragraph": [{"text": "160,000", "word": ["160,000"], "bounding_poly": [[[41, 51], [91, 51], [91, 64], [41, 64]]]}], "bounding_poly": [[[41, 51], [91, 51], [91, 64], [41, 64]]]}, {"text": "140,000", "paragraph": [{"text": "140,000", "word": ["140,000"], "bounding_poly": [[[40, 77], [85, 77], [85, 92], [40, 92]]]}], "bounding_poly": [[[40, 77], [85, 77], [85, 92], [40, 92]]]}, {"text": "Rods", "paragraph": [{"text": "Rods", "word": ["Rods"], "bounding_poly": [[[165, 82], [199, 83], [199, 101], [165, 100]]]}], "bounding_poly": [[[165, 82], [199, 83], [199, 101], [165, 100]]]}, {"text": "Rods", "paragraph": [{"text": "Rods", "word": ["Rods"], "bounding_poly": [[[436, 85], [472, 85], [472, 100], [436, 100]]]}], "bounding_poly": [[[436, 85], [472, 85], [472, 100], [436, 100]]]}, {"text": "120,000", "paragraph": [{"text": "120,000", "word": ["120,000"], "bounding_poly": [[[41, 105], [92, 105], [92, 119], [41, 119]]]}], "bounding_poly": [[[41, 105], [92, 105], [92, 119], [41, 119]]]}, {"text": "Number of receptors per square millimeter", "paragraph": [{"text": "Number of receptors per square millimeter", "word": ["Number", "of", "receptors", "per", "square", "millimeter"], "bounding_poly": [[[-3, 222], [-2, 166], [15, 166], [14, 222]], [[-1, 161], [-1, 147], [15, 147], [15, 161]], [[-1, 143], [0, 81], [16, 81], [15, 143]], [[18, 226], [17, 205], [33, 205], [34, 226]], [[17, 200], [16, 155], [33, 155], [34, 200]], [[16, 150], [14, 77], [31, 77], [33, 150]]]}], "bounding_poly": [[[-3, 226], [-3, 77], [34, 77], [34, 226]]]}, {"text": "100,000 80,000", "paragraph": [{"text": "100,000 80,000", "word": ["100,000", "80,000"], "bounding_poly": [[[41, 132], [86, 132], [86, 147], [41, 147]], [[45, 158], [85, 158], [85, 173], [45, 173]]]}], "bounding_poly": [[[41, 132], [86, 132], [86, 173], [41, 173]]]}, {"text": "60,000", "paragraph": [{"text": "60,000", "word": ["60,000"], "bounding_poly": [[[44, 186], [85, 186], [85, 201], [44, 201]]]}], "bounding_poly": [[[44, 186], [85, 186], [85, 201], [44, 201]]]}, {"text": "40,000", "paragraph": [{"text": "40,000", "word": ["40,000"], "bounding_poly": [[[44, 214], [85, 214], [85, 228], [44, 228]]]}], "bounding_poly": [[[44, 214], [85, 214], [85, 228], [44, 228]]]}, {"text": "20,000", "paragraph": [{"text": "20,000", "word": ["20,000"], "bounding_poly": [[[46, 241], [85, 241], [85, 254], [46, 254]]]}], "bounding_poly": [[[46, 241], [85, 241], [85, 254], [46, 254]]]}, {"text": "Cones", "paragraph": [{"text": "Cones", "word": ["Cones"], "bounding_poly": [[[445, 242], [487, 242], [487, 255], [445, 255]]]}], "bounding_poly": [[[445, 242], [487, 242], [487, 255], [445, 255]]]}, {"text": "0+", "paragraph": [{"text": "0+", "word": ["0+"], "bounding_poly": [[[80, 266], [101, 269], [99, 283], [78, 280]]]}], "bounding_poly": [[[80, 266], [101, 269], [99, 283], [78, 280]]]}, {"text": "80 \u00b0 70 \u00b0 60 \u00b0 50 \u00b0 40 \u00b0 30 \u00b0 20 \u00b0 10 \u00b0 0 \u00b0 10 \u00b0 20 \u00b0 30 \u00b0 400 500 60 \u00b0 70 \u00b0 Nasal retina Angle ( deg ) Temporal retina", "paragraph": [{"text": "80 \u00b0 70 \u00b0 60 \u00b0 50 \u00b0 40 \u00b0 30 \u00b0 20 \u00b0 10 \u00b0 0 \u00b0 10 \u00b0 20 \u00b0 30 \u00b0 400 500 60 \u00b0 70 \u00b0 Nasal retina", "word": ["80", "\u00b0", "70", "\u00b0", "60", "\u00b0", "50", "\u00b0", "40", "\u00b0", "30", "\u00b0", "20", "\u00b0", "10", "\u00b0", "0", "\u00b0", "10", "\u00b0", "20", "\u00b0", "30", "\u00b0", "400", "500", "60", "\u00b0", "70", "\u00b0", "Nasal", "retina"], "bounding_poly": [[[86, 286], [97, 286], [97, 298], [86, 298]], [[102, 286], [104, 286], [104, 298], [102, 298]], [[119, 286], [130, 286], [130, 298], [119, 298]], [[135, 286], [137, 286], [137, 298], [135, 298]], [[151, 286], [163, 286], [163, 298], [151, 298]], [[168, 286], [170, 286], [170, 298], [168, 298]], [[184, 286], [197, 286], [197, 298], [184, 298]], [[199, 286], [203, 286], [203, 298], [199, 298]], [[217, 286], [230, 286], [230, 298], [217, 298]], [[232, 286], [236, 286], [236, 298], [232, 298]], [[250, 286], [263, 286], [263, 298], [250, 298]], [[265, 286], [269, 286], [269, 298], [265, 298]], [[283, 286], [294, 286], [294, 298], [283, 298]], [[299, 286], [301, 286], [301, 298], [299, 298]], [[316, 286], [327, 286], [327, 298], [316, 298]], [[332, 286], [334, 286], [334, 298], [332, 298]], [[351, 286], [357, 286], [357, 296], [351, 296]], [[359, 286], [363, 286], [363, 296], [359, 296]], [[382, 284], [393, 284], [393, 298], [382, 298]], [[398, 284], [400, 284], [400, 298], [398, 298]], [[414, 284], [427, 284], [427, 298], [414, 298]], [[429, 284], [434, 284], [434, 298], [429, 298]], [[447, 284], [460, 284], [460, 298], [447, 298]], [[462, 284], [467, 284], [467, 298], [462, 298]], [[480, 284], [500, 284], [500, 298], [480, 298]], [[513, 284], [533, 284], [533, 298], [513, 298]], [[545, 284], [559, 284], [559, 298], [545, 298]], [[561, 284], [565, 284], [565, 298], [561, 298]], [[578, 284], [592, 284], [592, 298], [578, 298]], [[594, 284], [598, 284], [598, 298], [594, 298]], [[122, 302], [159, 302], [159, 317], [122, 317]], [[164, 302], [203, 302], [203, 317], [164, 317]]]}, {"text": "Angle ( deg )", "word": ["Angle", "(", "deg", ")"], "bounding_poly": [[[303, 301], [342, 301], [342, 318], [303, 318]], [[346, 301], [351, 301], [351, 318], [346, 318]], [[353, 301], [374, 301], [374, 318], [353, 318]], [[377, 301], [380, 301], [380, 318], [377, 318]]]}, {"text": "Temporal retina", "word": ["Temporal", "retina"], "bounding_poly": [[[468, 302], [534, 301], [534, 318], [468, 319]], [[540, 301], [579, 300], [579, 317], [540, 318]]]}], "bounding_poly": [[[86, 284], [598, 284], [598, 317], [86, 317]], [[303, 300], [380, 301], [380, 319], [303, 318]], [[468, 302], [579, 300], [579, 317], [468, 319]]]}], "bounding_poly": [[[41, 24], [84, 24], [84, 38], [41, 38]], [[325, 35], [400, 38], [399, 55], [324, 52]], [[41, 51], [91, 51], [91, 64], [41, 64]], [[40, 77], [85, 77], [85, 92], [40, 92]], [[165, 82], [199, 83], [199, 101], [165, 100]], [[436, 85], [472, 85], [472, 100], [436, 100]], [[41, 105], [92, 105], [92, 119], [41, 119]], [[-3, 226], [-3, 77], [34, 77], [34, 226]], [[41, 132], [86, 132], [86, 173], [41, 173]], [[44, 186], [85, 186], [85, 201], [44, 201]], [[44, 214], [85, 214], [85, 228], [44, 228]], [[46, 241], [85, 241], [85, 254], [46, 254]], [[445, 242], [487, 242], [487, 255], [445, 255]], [[80, 266], [101, 269], [99, 283], [78, 280]], [[86, 284], [598, 284], [598, 319], [86, 319]]]}